diracx/db/__init__.py
diracx/db/__main__.py
diracx/db/exceptions.py
diracx/db/py.typed
diracx/db/os/__init__.py
diracx/db/os/job_parameters.py
diracx/db/os/utils.py
diracx/db/sql/__init__.py
diracx/db/sql/auth/__init__.py
diracx/db/sql/auth/db.py
diracx/db/sql/auth/schema.py
diracx/db/sql/dummy/__init__.py
diracx/db/sql/dummy/db.py
diracx/db/sql/dummy/schema.py
diracx/db/sql/job/__init__.py
diracx/db/sql/job/db.py
diracx/db/sql/job/schema.py
diracx/db/sql/job_logging/__init__.py
diracx/db/sql/job_logging/db.py
diracx/db/sql/job_logging/schema.py
diracx/db/sql/pilot_agents/__init__.py
diracx/db/sql/pilot_agents/db.py
diracx/db/sql/pilot_agents/schema.py
diracx/db/sql/sandbox_metadata/__init__.py
diracx/db/sql/sandbox_metadata/db.py
diracx/db/sql/sandbox_metadata/schema.py
diracx/db/sql/task_queue/__init__.py
diracx/db/sql/task_queue/db.py
diracx/db/sql/task_queue/schema.py
diracx/db/sql/utils/__init__.py
diracx/db/sql/utils/base.py
diracx/db/sql/utils/functions.py
diracx/db/sql/utils/types.py
diracx_db-0.0.7.dist-info/METADATA
diracx_db-0.0.7.dist-info/WHEEL
diracx_db-0.0.7.dist-info/entry_points.txt
diracx_db-0.0.7.dist-info/RECORD
